SpringMvcKuangjiaRumenjiaochengCYuyanBianchengWangFix1/README.md
SpringMvcKuangjiaRumenjiaochengCYuyanBianchengWangFix1/__init__.py
SpringMvcKuangjiaRumenjiaochengCYuyanBianchengWangFix1/__main__.py
SpringMvcKuangjiaRumenjiaochengCYuyanBianchengWangFix1/file.epub
SpringMvcKuangjiaRumenjiaochengCYuyanBianchengWangFix1/index.html
SpringMvcKuangjiaRumenjiaochengCYuyanBianchengWangFix1/css/__init__.py
SpringMvcKuangjiaRumenjiaochengCYuyanBianchengWangFix1/css/annotations.css
SpringMvcKuangjiaRumenjiaochengCYuyanBianchengWangFix1/css/main.css
SpringMvcKuangjiaRumenjiaochengCYuyanBianchengWangFix1/css/normalize.css
SpringMvcKuangjiaRumenjiaochengCYuyanBianchengWangFix1/css/popup.css
SpringMvcKuangjiaRumenjiaochengCYuyanBianchengWangFix1/font/__init__.py
SpringMvcKuangjiaRumenjiaochengCYuyanBianchengWangFix1/font/fontello.eot
SpringMvcKuangjiaRumenjiaochengCYuyanBianchengWangFix1/font/fontello.svg
SpringMvcKuangjiaRumenjiaochengCYuyanBianchengWangFix1/font/fontello.ttf
SpringMvcKuangjiaRumenjiaochengCYuyanBianchengWangFix1/font/fontello.woff
SpringMvcKuangjiaRumenjiaochengCYuyanBianchengWangFix1/img/__init__.py
SpringMvcKuangjiaRumenjiaochengCYuyanBianchengWangFix1/img/annotator-glyph-sprite.png
SpringMvcKuangjiaRumenjiaochengCYuyanBianchengWangFix1/img/annotator-icon-sprite.png
SpringMvcKuangjiaRumenjiaochengCYuyanBianchengWangFix1/img/apple-touch-icon.png
SpringMvcKuangjiaRumenjiaochengCYuyanBianchengWangFix1/img/cancelfullscreen.png
SpringMvcKuangjiaRumenjiaochengCYuyanBianchengWangFix1/img/close.png
SpringMvcKuangjiaRumenjiaochengCYuyanBianchengWangFix1/img/fullscreen.png
SpringMvcKuangjiaRumenjiaochengCYuyanBianchengWangFix1/img/loader.gif
SpringMvcKuangjiaRumenjiaochengCYuyanBianchengWangFix1/img/menu-icon.png
SpringMvcKuangjiaRumenjiaochengCYuyanBianchengWangFix1/img/save.png
SpringMvcKuangjiaRumenjiaochengCYuyanBianchengWangFix1/img/saved.png
SpringMvcKuangjiaRumenjiaochengCYuyanBianchengWangFix1/img/settings-s.png
spring_mvc_kuangjia_rumenjiaocheng_c_yuyan_biancheng_wang_fix1-2025.3.24.0.dist-info/METADATA
spring_mvc_kuangjia_rumenjiaocheng_c_yuyan_biancheng_wang_fix1-2025.3.24.0.dist-info/WHEEL
spring_mvc_kuangjia_rumenjiaocheng_c_yuyan_biancheng_wang_fix1-2025.3.24.0.dist-info/entry_points.txt
spring_mvc_kuangjia_rumenjiaocheng_c_yuyan_biancheng_wang_fix1-2025.3.24.0.dist-info/top_level.txt
spring_mvc_kuangjia_rumenjiaocheng_c_yuyan_biancheng_wang_fix1-2025.3.24.0.dist-info/RECORD
